bartiq/__init__.py
bartiq/_routine.py
bartiq/analysis/__init__.py
bartiq/analysis/decompose_resources.py
bartiq/analysis/optimization.py
bartiq/analysis/rewriters/__init__.py
bartiq/analysis/rewriters/expression.py
bartiq/analysis/rewriters/routine_rewriter.py
bartiq/analysis/rewriters/sympy_expression.py
bartiq/analysis/rewriters/utils.py
bartiq/compilation/__init__.py
bartiq/compilation/_common.py
bartiq/compilation/_compile.py
bartiq/compilation/_evaluate.py
bartiq/compilation/derived_resources.py
bartiq/compilation/postprocessing.py
bartiq/compilation/preprocessing.py
bartiq/errors.py
bartiq/integrations/__init__.py
bartiq/integrations/jupyter/__init__.py
bartiq/integrations/jupyter/routine_explorer.py
bartiq/integrations/latex.py
bartiq/py.typed
bartiq/repetitions.py
bartiq/symbolics/__init__.py
bartiq/symbolics/ast_parser.py
bartiq/symbolics/backend.py
bartiq/symbolics/interpreter.py
bartiq/symbolics/sympy_backend.py
bartiq/symbolics/sympy_interpreter.py
bartiq/symbolics/sympy_serializer.py
bartiq/transform.py
bartiq/verification.py
bartiq/visualizations.py
bartiq-0.15.3.dist-info/LICENSE
bartiq-0.15.3.dist-info/METADATA
bartiq-0.15.3.dist-info/WHEEL
bartiq-0.15.3.dist-info/RECORD
