Metadata-Version: 2.1
Name: bartiq
Version: 0.15.3
Summary: Symbolic Quantum Resource Estimation compilation
License: Apache 2.0
Author: PsiQuantum, Corp.
Requires-Python: >=3.10,<4.0
Classifier: License :: Other/Proprietary License
Classifier: Programming Language :: Python :: 3
Classifier: Programming Language :: Python :: 3.10
Classifier: Programming Language :: Python :: 3.11
Classifier: Programming Language :: Python :: 3.12
Provides-Extra: interactive
Provides-Extra: jupyter
Provides-Extra: optimization
Requires-Dist: ipytree (>=0.2.2,<0.3.0) ; extra == "jupyter" or extra == "interactive"
Requires-Dist: ipywidgets (>=8.1.2,<9.0.0) ; extra == "jupyter" or extra == "interactive"
Requires-Dist: pandas (>=2.2,<3.0) ; extra == "interactive"
Requires-Dist: plotly (>=5.17,<6.0) ; extra == "interactive"
Requires-Dist: pydantic (>=2.7,<3.0)
Requires-Dist: qref (>=0.11.0,<0.12.0)
Requires-Dist: scipy (>=1.14.1,<2.0.0) ; extra == "optimization"
Requires-Dist: sympy (>=1.12,<2.0)
Requires-Dist: traitlets (>=5.14.3,<6.0.0) ; extra == "jupyter" or extra == "interactive"
